bionemo/scdl/__init__.py
bionemo/scdl/api/__init__.py
bionemo/scdl/api/single_cell_row_dataset.py
bionemo/scdl/data/__init__.py
bionemo/scdl/data/load.py
bionemo/scdl/data/resources/scdl.yaml
bionemo/scdl/index/__init__.py
bionemo/scdl/index/row_feature_index.py
bionemo/scdl/io/__init__.py
bionemo/scdl/io/single_cell_collection.py
bionemo/scdl/io/single_cell_memmap_dataset.py
bionemo/scdl/schema/__init__.py
bionemo/scdl/schema/header.py
bionemo/scdl/schema/headerutil.py
bionemo/scdl/schema/magic.py
bionemo/scdl/schema/version.py
bionemo/scdl/scripts/__init__.py
bionemo/scdl/scripts/convert_h5ad_to_scdl.py
bionemo/scdl/util/__init__.py
bionemo/scdl/util/async_worker_queue.py
bionemo/scdl/util/filecopyutil.py
bionemo/scdl/util/memmap_utils.py
bionemo/scdl/util/scdl_constants.py
bionemo/scdl/util/torch_dataloader_utils.py
bionemo_scdl-0.1.3.dist-info/licenses/LICENSE
bionemo_scdl-0.1.3.dist-info/METADATA
bionemo_scdl-0.1.3.dist-info/WHEEL
bionemo_scdl-0.1.3.dist-info/entry_points.txt
bionemo_scdl-0.1.3.dist-info/top_level.txt
bionemo_scdl-0.1.3.dist-info/RECORD
