Metadata-Version: 2.4
Name: bionemo-scdl
Version: 0.1.3
Summary: SCDL, a Dataset class for Single Cell data.
Author-email: BioNeMo Team <bionemofeedback@nvidia.com>
License: 
Requires-Python: >=3.10
License-File: LICENSE
Requires-Dist: anndata>=0.12.1
Requires-Dist: numpy>=1.24.4
Requires-Dist: pandas>=2.2.1
Requires-Dist: pyarrow>=16.0.0
Requires-Dist: pooch>=1.6.0
Requires-Dist: scipy>=1.11.1
Requires-Dist: torch>=2.2.1
Requires-Dist: pydantic[email]>=2.2.0
Requires-Dist: tqdm>=4.67.1
Requires-Dist: psutil>=7.0.0
Provides-Extra: test
Requires-Dist: pytest>=8.4.1; extra == "test"
Requires-Dist: nest-asyncio>=1.6.0; extra == "test"
Requires-Dist: ngcsdk>=4.3.0; extra == "test"
Dynamic: license-file
